peek_agent
