Metadata-Version: 1.1
Name: peek-agent
Version: 1.3.1
Summary: Peek Platform - Agent Service
Home-page: https://github.com/Synerty/peek-agent
Author: Synerty
Author-email: contact@synerty.com
License: UNKNOWN
Download-URL: https://github.com/Synerty/peek-agent/tarball/1.3.1
Keywords: Peek,Python,Platform,synerty
Platform: UNKNOWN
Classifier: Programming Language :: Python :: 3.5
